[{
        "_id": "AUMC",
        "name": "Amsterdam University Medical Centre",
        "type": "data",
        "status": 1,
        "cpu_count": 0,
        "cpu_percent": 0,
        "gpu_count": 0,
        "memory": {
            "available": 0,
            "total": 0
        },
        "outbound_connectivity": false,
        "inbound_ports_connectivity": false
    },
    {
        "_id": "BUCH",
        "name": "Bucharest Emergency Clinical Hospital",
        "type": "data",
        "status": 0,
        "cpu_count": 0,
        "cpu_percent": 0,
        "gpu_count": 0,
        "memory": {
            "available": 0,
            "total": 0
        },
        "outbound_connectivity": false,
        "inbound_ports_connectivity": false
    },
    {
        "_id": "GEM",
        "name": "Fondazione Policlinico A. Gemelli IRCCS",
        "type": "data",
        "status": 2,
        "cpu_count": 4,
        "cpu_percent": 10,
        "gpu_count": 1,
        "memory": {
            "available": 15,
            "total": 24
        },
        "outbound_connectivity": true,
        "inbound_ports_connectivity": false
    },
    {
        "_id": "ICRC",
        "name": "St. Anne's University Hospital Brno",
        "type": "data",
        "cpu_count": 4,
        "cpu_percent": 10,
        "gpu_count": 1,
        "memory": {
            "available": 16,
            "total": 16
        },
        "outbound_connectivity": true,
        "inbound_ports_connectivity": false,
        "status": 2
    },
    {
        "_id": "KUH",
        "name": "Karolinska University Hospital",
        "type": "data",
        "status": 2,
        "cpu_count": 2,
        "cpu_percent": 50,
        "gpu_count": 1,
        "memory": {
            "available": 16,
            "total": 32
        },
        "outbound_connectivity": true,
        "inbound_ports_connectivity": false
    },
    {
        "_id": "UCLH",
        "name": "University College London Hospital",
        "type": "data",
        "status": 2,
        "cpu_count": 4,
        "cpu_percent": 50,
        "gpu_count": 1,
        "memory": {
            "available": 32,
            "total": 32
        },
        "outbound_connectivity": true,
        "inbound_ports_connectivity": false
    },
    {
        "_id": "UMCU",
        "name": "University Medical Centre Utrecht",
        "type": "data",
        "status": 1,
        "cpu_count": 0,
        "cpu_percent": 0,
        "gpu_count": 0,
        "memory": {
            "available": 0,
            "total": 0
        },
        "outbound_connectivity": true,
        "inbound_ports_connectivity": false
    },
    {
        "_id": "VHIR",
        "name": "Vall d'Hebron Research Institute",
        "type": "data",
        "status": 0,
        "cpu_count": 0,
        "cpu_percent": 0,
        "gpu_count": 0,
        "memory": {
            "available": 0,
            "total": 0
        },
        "outbound_connectivity": false,
        "inbound_ports_connectivity": false
    }
]